{
  "carrera": "Bioquímica",
  "total_creditos": 330,
  "semestres": [
    {
      "numero": 1,
      "cursos": [
        {
          "id": 1,
          "codigo": "QG1",
          "nombre": "Química General I",
          "sct": 8,
          "prerrequisitos": [],
          "area": "quimica"
        },
        {
          "id": 2,
          "codigo": "TLQ",
          "nombre": "Técnicas de Laboratorio Químico",
          "sct": 4,
          "prerrequisitos": [],
          "area": "quimica"
        },
        {
          "id": 3,
          "codigo": "IAC",
          "nombre": "Introducción al Álgebra y Cálculo",
          "sct": 8,
          "prerrequisitos": [],
          "area": "matematica"
        },
        {
          "id": 4,
          "codigo": "QT",
          "nombre": "Química Transformadora",
          "sct": 3,
          "prerrequisitos": [],
          "area": "formacion"
        },
        {
          "id": 5,
          "codigo": "RCC",
          "nombre": "Razonamiento y Comunicación Científica",
          "sct": 4,
          "prerrequisitos": [],
          "area": "formacion"
        },
        {
          "id": 6,
          "codigo": "ING1",
          "nombre": "Inglés I",
          "sct": 3,
          "prerrequisitos": [],
          "area": "formacion"
        }
      ]
    },
    {
      "numero": 2,
      "cursos": [
        {
          "id": 7,
          "codigo": "QG2",
          "nombre": "Química General II",
          "sct": 5,
          "prerrequisitos": [1],
          "area": "quimica"
        },
        {
          "id": 8,
          "codigo": "LQG",
          "nombre": "Laboratorio de Química General",
          "sct": 3,
          "prerrequisitos": [1, 2],
          "area": "quimica"
        },
        {
          "id": 9,
          "codigo": "FG",
          "nombre": "Física General",
          "sct": 5,
          "prerrequisitos": [3],
          "area": "fisica"
        },
        {
          "id": 10,
          "codigo": "CDI",
          "nombre": "Cálculo Diferencial e Integral",
          "sct": 6,
          "prerrequisitos": [3],
          "area": "matematica"
        },
        {
          "id": 11,
          "codigo": "BC",
          "nombre": "Biología Celular",
          "sct": 5,
          "prerrequisitos": [2],
          "area": "biologia"
        },
        {
          "id": 12,
          "codigo": "CFG1",
          "nombre": "Curso de Formación General",
          "sct": 3,
          "prerrequisitos": [],
          "area": "formacion"
        },
        {
          "id": 13,
          "codigo": "ING2",
          "nombre": "Inglés II",
          "sct": 3,
          "prerrequisitos": [6],
          "area": "formacion"
        }
      ]
    },
    {
      "numero": 3,
      "cursos": [
        {
          "id": 14,
          "codigo": "QO1",
          "nombre": "Química Orgánica I",
          "sct": 5,
          "prerrequisitos": [7],
          "area": "quimica"
        },
        {
          "id": 15,
          "codigo": "QA1",
          "nombre": "Química Analítica I",
          "sct": 5,
          "prerrequisitos": [7, 8],
          "area": "quimica"
        },
        {
          "id": 16,
          "codigo": "LQO1",
          "nombre": "Laboratorio I de Química Orgánica",
          "sct": 4,
          "prerrequisitos": [7, 8],
          "area": "quimica"
        },
        {
          "id": 17,
          "codigo": "EAD",
          "nombre": "Estadística y Análisis de Datos",
          "sct": 4,
          "prerrequisitos": [10],
          "area": "matematica"
        },
        {
          "id": 18,
          "codigo": "FAB",
          "nombre": "Física Aplicada a la Bioquímica",
          "sct": 4,
          "prerrequisitos": [9],
          "area": "fisica"
        },
        {
          "id": 19,
          "codigo": "FC",
          "nombre": "Fisiología Celular",
          "sct": 5,
          "prerrequisitos": [9, 11],
          "area": "biologia"
        },
        {
          "id": 20,
          "codigo": "CC",
          "nombre": "Cultura Científica: Divulgación y Enseñanza",
          "sct": 3,
          "prerrequisitos": [4, 5],
          "area": "formacion"
        }
      ]
    },
    {
      "numero": 4,
      "cursos": [
        {
          "id": 21,
          "codigo": "QO2",
          "nombre": "Química Orgánica II",
          "sct": 5,
          "prerrequisitos": [14],
          "area": "quimica"
        },
        {
          "id": 22,
          "codigo": "LAQ",
          "nombre": "Laboratorio de Análisis Químico",
          "sct": 4,
          "prerrequisitos": [8, 15, 17],
          "area": "quimica"
        },
        {
          "id": 23,
          "codigo": "QA2",
          "nombre": "Química Analítica II",
          "sct": 5,
          "prerrequisitos": [15],
          "area": "quimica"
        },
        {
          "id": 24,
          "codigo": "FQ1",
          "nombre": "Fisicoquímica I",
          "sct": 6,
          "prerrequisitos": [9, 10, 14],
          "area": "quimica"
        },
        {
          "id": 25,
          "codigo": "FS",
          "nombre": "Fisiología de Sistemas",
          "sct": 4,
          "prerrequisitos": [19],
          "area": "biologia"
        },
        {
          "id": 26,
          "codigo": "TCC",
          "nombre": "Taller de Cultura Científica",
          "sct": 3,
          "prerrequisitos": [20],
          "area": "formacion"
        }
      ]
    },
    {
      "numero": 5,
      "cursos": [
        {
          "id": 27,
          "codigo": "LAI",
          "nombre": "Laboratorio de Análisis Instrumental",
          "sct": 4,
          "prerrequisitos": [22, 23],
          "area": "quimica"
        },
        {
          "id": 28,
          "codigo": "BG",
          "nombre": "Bioquímica General",
          "sct": 9,
          "prerrequisitos": [21, 24],
          "area": "biologia"
        },
        {
          "id": 29,
          "codigo": "EFOC",
          "nombre": "Estructura y Función de Organelos Celulares",
          "sct": 6,
          "prerrequisitos": [21, 25],
          "area": "biologia"
        },
        {
          "id": 30,
          "codigo": "FQCB",
          "nombre": "Fisicoquímica para Ciencias Biológicas",
          "sct": 7,
          "prerrequisitos": [18, 24],
          "area": "fisica"
        },
        {
          "id": 31,
          "codigo": "ING3",
          "nombre": "Inglés III",
          "sct": 3,
          "prerrequisitos": [13],
          "area": "formacion"
        }
      ]
    },
    {
      "numero": 6,
      "cursos": [
        {
          "id": 32,
          "codigo": "EFP",
          "nombre": "Estructura y Función de Proteínas",
          "sct": 8,
          "prerrequisitos": [29, 31],
          "area": "biologia"
        },
        {
          "id": 33,
          "codigo": "GM",
          "nombre": "Genética Molecular",
          "sct": 8,
          "prerrequisitos": [29],
          "area": "biologia"
        },
        {
          "id": 34,
          "codigo": "ICM",
          "nombre": "Inmunología Celular y Molecular",
          "sct": 7,
          "prerrequisitos": [30],
          "area": "biologia"
        },
        {
          "id": 35,
          "codigo": "MG",
          "nombre": "Microbiología General",
          "sct": 5,
          "prerrequisitos": [30],
          "area": "biologia"
        },
        {
          "id": 36,
          "codigo": "ING4",
          "nombre": "Inglés IV",
          "sct": 3,
          "prerrequisitos": [32],
          "area": "formacion"
        }
      ]
    },
    {
      "numero": 7,
      "cursos": [
        {
          "id": 37,
          "codigo": "QFP",
          "nombre": "Química Fisiológica y Patológica",
          "sct": 6,
          "prerrequisitos": [33, 35],
          "area": "quimica"
        },
        {
          "id": 38,
          "codigo": "GME",
          "nombre": "Genética Molecular de Eucariontes",
          "sct": 6,
          "prerrequisitos": [34],
          "area": "biologia"
        },
        {
          "id": 39,
          "codigo": "FGM",
          "nombre": "Fisiología y Genética Microbiana",
          "sct": 8,
          "prerrequisitos": [34, 36],
          "area": "biologia"
        },
        {
          "id": 40,
          "codigo": "AG",
          "nombre": "Administración y Gestión",
          "sct": 4,
          "prerrequisitos": [26],
          "area": "formacion"
        },
        {
          "id": 41,
          "codigo": "UIB",
          "nombre": "Unidad de Investigación en Bioquímica",
          "sct": 6,
          "prerrequisitos": [28, 29],
          "area": "otros"
        }
      ]
    },
    {
      "numero": 8,
      "cursos": [
        {
          "id": 42,
          "codigo": "BCP",
          "nombre": "Bioquímica Clínica y Patológica",
          "sct": 8,
          "prerrequisitos": [38],
          "area": "biologia"
        },
        {
          "id": 43,
          "codigo": "FBV",
          "nombre": "Fisiología y Bioquímica Vegetal",
          "sct": 4,
          "prerrequisitos": [39],
          "area": "biologia"
        },
        {
          "id": 44,
          "codigo": "BIOE",
          "nombre": "Bioética",
          "sct": 3,
          "prerrequisitos": [38],
          "area": "formacion"
        },
        {
          "id": 45,
          "codigo": "FEP",
          "nombre": "Formulación y Evaluación de Proyectos Científicos",
          "sct": 4,
          "prerrequisitos": [33],
          "area": "formacion"
        },
        {
          "id": 46,
          "codigo": "BIOI",
          "nombre": "Bioinformática",
          "sct": 5,
          "prerrequisitos": [33, 39],
          "area": "otros"
        },
        {
          "id": 47,
          "codigo": "PP1",
          "nombre": "Práctica Profesional I",
          "sct": 6,
          "prerrequisitos": [33, 34],
          "area": "otros"
        }
      ]
    },
    {
      "numero": 9,
      "cursos": [
        {
          "id": 48,
          "codigo": "LBC",
          "nombre": "Laboratorio de Bioquímica Clínica",
          "sct": 6,
          "prerrequisitos": [41, 43],
          "area": "quimica"
        },
        {
          "id": 49,
          "codigo": "TF",
          "nombre": "Tópicos de Farmacología",
          "sct": 4,
          "prerrequisitos": [43, 45],
          "area": "biologia"
        },
        {
          "id": 50,
          "codigo": "BIOT",
          "nombre": "Biotecnología",
          "sct": 6,
          "prerrequisitos": [43, 45],
          "area": "otros"
        },
        {
          "id": 51,
          "codigo": "ELEC1",
          "nombre": "Electivo Especializado",
          "sct": 4,
          "prerrequisitos": [],
          "area": "otros"
        },
        {
          "id": 52,
          "codigo": "ELEC2",
          "nombre": "Electivo Especializado",
          "sct": 4,
          "prerrequisitos": [],
          "area": "otros"
        }
      ]
    },
    {
      "numero": 10,
      "cursos": [
        {
          "id": 53,
          "codigo": "PP2",
          "nombre": "Práctica Profesional II",
          "sct": 6,
          "prerrequisitos": [43, 47, 48],
          "area": "otros"
        },
        {
          "id": 54,
          "codigo": "UIAB",
          "nombre": "Unidad de Investigación Avanzada en Bioquímica",
          "sct": 7,
          "prerrequisitos": [42, 49, 51],
          "area": "otros"
        },
        {
          "id": 55,
          "codigo": "BPI",
          "nombre": "Bioprocesos Industriales",
          "sct": 6,
          "prerrequisitos": [41, 51],
          "area": "otros"
        },
        {
          "id": 56,
          "codigo": "ELEC3",
          "nombre": "Electivo Especializado",
          "sct": 4,
          "prerrequisitos": [],
          "area": "otros"
        },
        {
          "id": 57,
          "codigo": "ELEC4",
          "nombre": "Electivo Especializado",
          "sct": 5,
          "prerrequisitos": [],
          "area": "otros"
        }
      ]
    },
    {
      "numero": 11,
      "cursos": [
        {
          "id": 58,
          "codigo": "PMT",
          "nombre": "Proyecto de Memoria de Título",
          "sct": 8,
          "prerrequisitos": [46, 49, 50, 51],
          "area": "otros"
        },
        {
          "id": 59,
          "codigo": "MT",
          "nombre": "Memoria de Título",
          "sct": 30,
          "prerrequisitos": [58],
          "area": "otros"
        }
      ]
    }
  ]
}
